sequence_detector__fsm-main/101_sequence_dtector/design.v
module seq_detector(out,in,clk,rst);
input in,clk,rst;
output reg out;

reg [1:0] present;
reg [1:0] next;

parameter [1:0] s0 = 2'b00;
parameter [1:0] s1 = 2'b01;
parameter [1:0] s2 = 2'b10;
parameter [1:0] s3 = 2'b11;

always @ (posedge clk)
begin
  if(rst)
  begin
  out = 1'b0;
  present = s0;
  next = s0;
  end
  else
  begin
    present = next;

    case(present)

    s0 : begin
      out <= 1'b0;
      if(in)
      begin
        next = s1;
      end
      else
      begin
        next = s0;
      end
    end

    s1 : begin
      out <= 1'b0;
      if(in)
      begin
        next = s1;
      end
      else
      begin
        next = s2;
      end
    end

    s2 : begin
      out <= 1'b0;
      if(in)
      begin
        next = s3;
      end
      else
      begin
        next = s0;
      end
    end

    s3 : begin
      out <= 1'b1;
      if(in)
      begin
        next = s1;
      end
      else
      begin
        next = s0;
      end
    end
    
    endcase
  end
end

endmodule

sequence_detector__fsm-main/101_sequence_dtector/test.v
`include "design.v"
module test();

reg in,clk,rst;
wire out;

seq_detector s1 (out,in,clk,rst);

initial
begin
  
  $dumpfile("seqwave.vcd");
  $dumpvars(0,test);

  //initialization of values

  clk = 1;
  rst = 1;
  in = 1;
  #10;
  $display("output is : %d",out);
  #20;
  rst = 0;
  #10;
  in = 1;
  #10;
  $display("output is : %d",out);
  #10;
  in = 0;
  #10;
  $display("output is : %d",out);
  #10;
  in = 1;
  #10;
  $display("output is : %d",out);
  #10;
  in = 1;
  #10;
  $display("output is : %d",out);
  #10;
  in = 0;
  #10;
  $display("output is : %d",out);
  #10;
  in = 1;
  #10;
  $display("output is : %d",out);
  #10;
  in = 0;
  #10;
  $display("output is : %d",out);
  #10;
  in = 1;
  #10;
  $display("output is : %d",out);
  #10;
  in = 1;
  #10;
  $display("output is : %d",out);
  #10;
  in = 1;
  #10;
  $display("output is : %d",out);
  #10;

  $finish;
end

always #10 clk = ~clk;

endmodule

sequence_detector__fsm-main/101_sequence_dtector/seqwave.vcd
$date
	Mon Sep 23 23:34:13 2024
$end
$version
	Icarus Verilog
$end
$timescale
	1s
$end
$scope module test $end
$var wire 1 ! out $end
$var reg 1 " clk $end
$var reg 1 # in $end
$var reg 1 $ rst $end
$scope module s1 $end
$var wire 1 " clk $end
$var wire 1 # in $end
$var wire 1 $ rst $end
$var parameter 2 % s0 $end
$var parameter 2 & s1 $end
$var parameter 2 ' s2 $end
$var parameter 2 ( s3 $end
$var reg 2 ) next [1:0] $end
$var reg 1 ! out $end
$var reg 2 * present [1:0] $end
$upscope $end
$upscope $end
$enddefinitions $end
$comment Show the parameter values. $end
$dumpall
b11 (
b10 '
b1 &
b0 %
$end
#0
$dumpvars
b0 *
b0 )
1$
1#
1"
0!
$end
#10
0"
#20
1"
#30
0"
0$
#40
b1 )
1"
#50
0"
#60
b10 )
b1 *
1"
0#
#70
0"
#80
b11 )
b10 *
1"
1#
#90
0"
#100
1!
b1 )
b11 *
1"
#110
0"
#120
0!
b10 )
b1 *
1"
0#
#130
0"
#140
b11 )
b10 *
1"
1#
#150
0"
#160
1!
b0 )
b11 *
1"
0#
#170
0"
#180
0!
b1 )
b0 *
1"
1#
#190
0"
#200
b1 *
1"
